LICENSE
README.md
pyproject.toml
setup.cfg
setup.py
src/dox/__init__.py
src/dox/dox.py
src/dox/mapper.py
src/dox/candidate_network/__init__.py
src/dox/candidate_network/candidate_network.py
src/dox/candidate_network/candidate_network_handler.py
src/dox/database/__init__.py
src/dox/database/mongo_handler.py
src/dox/database/mongo_iter.py
src/dox/evaluation/__init__.py
src/dox/evaluation/evaluation_handler.py
src/dox/evaluation/evaluation_report.py
src/dox/index/__init__.py
src/dox/index/babel_hash.py
src/dox/index/index_build.py
src/dox/index/index_handler.py
src/dox/index/schema_graph.py
src/dox/index/schema_index.py
src/dox/index/value_index.py
src/dox/keyword_match/__init__.py
src/dox/keyword_match/keyword_match.py
src/dox/keyword_match/keyword_match_handler.py
src/dox/query_match/__init__.py
src/dox/query_match/query_match.py
src/dox/query_match/query_match_handler.py
src/dox/utils/__init__.py
src/dox/utils/config_handler.py
src/dox/utils/document_traverser.py
src/dox/utils/generate_evaluation_report.py
src/dox/utils/graph.py
src/dox/utils/keyword_query.py
src/dox/utils/logger.py
src/dox/utils/memory.py
src/dox/utils/mongo_query_builder.py
src/dox/utils/ordinal.py
src/dox/utils/plots.py
src/dox/utils/printmd.py
src/dox/utils/result.py
src/dox/utils/shift_tab.py
src/dox/utils/similarity.py
src/dox/utils/tf_iaf.py
src/dox/utils/timestr.py
src/dox/utils/tokenizer.py
src/dox/utils/truncate.py
src/dox/utils/utils.py
src/dox_search.egg-info/PKG-INFO
src/dox_search.egg-info/SOURCES.txt
src/dox_search.egg-info/dependency_links.txt
src/dox_search.egg-info/requires.txt
src/dox_search.egg-info/top_level.txt